{
  "scriptId": "458",
  "url": "file:///home/joyja/.cache/deno/npm/registry.npmjs.org/drizzle-orm/0.33.0/sql/expressions/conditions.js",
  "functions": [
    {
      "functionName": "",
      "ranges": [{ "startOffset": 0, "endOffset": 4573, "count": 1 }],
      "isBlockCoverage": true
    },
    {
      "functionName": "bindIfParam",
      "ranges": [{ "startOffset": 249, "endOffset": 518, "count": 0 }],
      "isBlockCoverage": false
    },
    {
      "functionName": "eq",
      "ranges": [{ "startOffset": 530, "endOffset": 603, "count": 0 }],
      "isBlockCoverage": false
    },
    {
      "functionName": "ne",
      "ranges": [{ "startOffset": 616, "endOffset": 690, "count": 0 }],
      "isBlockCoverage": false
    },
    {
      "functionName": "and",
      "ranges": [{ "startOffset": 692, "endOffset": 1065, "count": 0 }],
      "isBlockCoverage": false
    },
    {
      "functionName": "or",
      "ranges": [{ "startOffset": 1066, "endOffset": 1437, "count": 0 }],
      "isBlockCoverage": false
    },
    {
      "functionName": "not",
      "ranges": [{ "startOffset": 1438, "endOffset": 1497, "count": 0 }],
      "isBlockCoverage": false
    },
    {
      "functionName": "gt",
      "ranges": [{ "startOffset": 1509, "endOffset": 1582, "count": 0 }],
      "isBlockCoverage": false
    },
    {
      "functionName": "gte",
      "ranges": [{ "startOffset": 1596, "endOffset": 1670, "count": 0 }],
      "isBlockCoverage": false
    },
    {
      "functionName": "lt",
      "ranges": [{ "startOffset": 1683, "endOffset": 1756, "count": 0 }],
      "isBlockCoverage": false
    },
    {
      "functionName": "lte",
      "ranges": [{ "startOffset": 1770, "endOffset": 1844, "count": 0 }],
      "isBlockCoverage": false
    },
    {
      "functionName": "inArray",
      "ranges": [{ "startOffset": 1846, "endOffset": 2113, "count": 0 }],
      "isBlockCoverage": false
    },
    {
      "functionName": "notInArray",
      "ranges": [{ "startOffset": 2114, "endOffset": 2391, "count": 0 }],
      "isBlockCoverage": false
    },
    {
      "functionName": "isNull",
      "ranges": [{ "startOffset": 2392, "endOffset": 2450, "count": 0 }],
      "isBlockCoverage": false
    },
    {
      "functionName": "isNotNull",
      "ranges": [{ "startOffset": 2451, "endOffset": 2516, "count": 0 }],
      "isBlockCoverage": false
    },
    {
      "functionName": "exists",
      "ranges": [{ "startOffset": 2517, "endOffset": 2580, "count": 0 }],
      "isBlockCoverage": false
    },
    {
      "functionName": "notExists",
      "ranges": [{ "startOffset": 2581, "endOffset": 2651, "count": 0 }],
      "isBlockCoverage": false
    },
    {
      "functionName": "between",
      "ranges": [{ "startOffset": 2652, "endOffset": 2795, "count": 0 }],
      "isBlockCoverage": false
    },
    {
      "functionName": "notBetween",
      "ranges": [{ "startOffset": 2796, "endOffset": 2946, "count": 0 }],
      "isBlockCoverage": false
    },
    {
      "functionName": "like",
      "ranges": [{ "startOffset": 2947, "endOffset": 3018, "count": 0 }],
      "isBlockCoverage": false
    },
    {
      "functionName": "notLike",
      "ranges": [{ "startOffset": 3019, "endOffset": 3097, "count": 0 }],
      "isBlockCoverage": false
    },
    {
      "functionName": "ilike",
      "ranges": [{ "startOffset": 3098, "endOffset": 3171, "count": 0 }],
      "isBlockCoverage": false
    },
    {
      "functionName": "notIlike",
      "ranges": [{ "startOffset": 3172, "endOffset": 3252, "count": 0 }],
      "isBlockCoverage": false
    },
    {
      "functionName": "arrayContains",
      "ranges": [{ "startOffset": 3253, "endOffset": 3588, "count": 0 }],
      "isBlockCoverage": false
    },
    {
      "functionName": "arrayContained",
      "ranges": [{ "startOffset": 3589, "endOffset": 3926, "count": 0 }],
      "isBlockCoverage": false
    },
    {
      "functionName": "arrayOverlaps",
      "ranges": [{ "startOffset": 3927, "endOffset": 4262, "count": 0 }],
      "isBlockCoverage": false
    }
  ]
}
