{
  "scriptId": "382",
  "url": "file:///home/joyja/.cache/deno/npm/registry.npmjs.org/drizzle-orm/0.33.0/pg-core/table.js",
  "functions": [
    {
      "functionName": "",
      "ranges": [{ "startOffset": 0, "endOffset": 1867, "count": 1 }],
      "isBlockCoverage": true
    },
    {
      "functionName": "<static_initializer>",
      "ranges": [{ "startOffset": 181, "endOffset": 311, "count": 1 }],
      "isBlockCoverage": true
    },
    {
      "functionName": "<instance_members_initializer>",
      "ranges": [{ "startOffset": 333, "endOffset": 422, "count": 1 }],
      "isBlockCoverage": true
    },
    {
      "functionName": "pgTableWithSchema",
      "ranges": [{ "startOffset": 426, "endOffset": 1435, "count": 1 }],
      "isBlockCoverage": true
    },
    {
      "functionName": "",
      "ranges": [{ "startOffset": 639, "endOffset": 885, "count": 9 }],
      "isBlockCoverage": true
    },
    {
      "functionName": "",
      "ranges": [{ "startOffset": 981, "endOffset": 1154, "count": 9 }],
      "isBlockCoverage": true
    },
    {
      "functionName": "pgTable",
      "ranges": [{ "startOffset": 1452, "endOffset": 1551, "count": 1 }],
      "isBlockCoverage": true
    },
    {
      "functionName": "pgTableCreator",
      "ranges": [{ "startOffset": 1553, "endOffset": 1740, "count": 0 }],
      "isBlockCoverage": false
    }
  ]
}
